sc2_replay_analyzer/__init__.py
sc2_replay_analyzer/cli.py
sc2_replay_analyzer/commands.py
sc2_replay_analyzer/completer.py
sc2_replay_analyzer/config.py
sc2_replay_analyzer/db.py
sc2_replay_analyzer/parser.py
sc2_replay_analyzer/ui.py
sc2_replay_analyzer-0.5.1.dist-info/LICENSE
sc2_replay_analyzer-0.5.1.dist-info/METADATA
sc2_replay_analyzer-0.5.1.dist-info/WHEEL
sc2_replay_analyzer-0.5.1.dist-info/entry_points.txt
sc2_replay_analyzer-0.5.1.dist-info/top_level.txt
sc2_replay_analyzer-0.5.1.dist-info/RECORD
