Metadata-Version: 2.1
Name: sc2-replay-analyzer
Version: 0.5.1
Summary: Analyze your StarCraft II replays with filtering, stats, and beautiful terminal output
Author: Yair Shachar
License: MIT
Project-URL: Homepage, https://github.com/YairShachar/sc2_replay_analyzer
Project-URL: Repository, https://github.com/YairShachar/sc2_replay_analyzer
Project-URL: Issues, https://github.com/YairShachar/sc2_replay_analyzer/issues
Keywords: starcraft,sc2,replay,analyzer,esports,gaming
Classifier: Development Status :: 4 - Beta
Classifier: Environment :: Console
Classifier: Intended Audience :: End Users/Desktop
Classifier: Operating System :: OS Independent
Classifier: Programming Language :: Python :: 3
Classifier: Programming Language :: Python :: 3.8
Classifier: Programming Language :: Python :: 3.9
Classifier: Programming Language :: Python :: 3.10
Classifier: Programming Language :: Python :: 3.11
Classifier: Programming Language :: Python :: 3.12
Classifier: Topic :: Games/Entertainment :: Real Time Strategy
Requires-Python: >=3.8
License-File: LICENSE
Requires-Dist: sc2reader>=1.8.0
Requires-Dist: rich>=13.0.0
Requires-Dist: tomli-w>=1.0.0
Requires-Dist: prompt-toolkit>=3.0.0
Requires-Dist: tomli>=2.0.0; python_version < "3.11"
Provides-Extra: dev
Requires-Dist: pytest>=7.0.0; extra == "dev"
Requires-Dist: pytest-cov>=4.0.0; extra == "dev"
